[
  {
    "name": "Tighnari",
    "birthday": "12/29",
    "constellation": "Vulpes Zerda",
    "title": "Verdant Strider",
    "vision": "Dendro",
    "affiliation": "Gandharva Ville",
    "versionRelease": 3,
    "images": {
      "gacha": "http://res.cloudinary.com/dusbvc8ox/image/upload/v1703520798/FlameForge/characters/character1703520818086.png",
      "card": "http://res.cloudinary.com/dusbvc8ox/image/upload/v1703520809/FlameForge/characters/character1703520828814.jpg",
      "profile": "http://res.cloudinary.com/dusbvc8ox/image/upload/v1703520821/FlameForge/characters/character1703520841679.webp"
    },
    "desc": "A young researcher well-versed in botany who currently serves as a Forest Watcher in Avidya Forest. He is a straight shooter with a warm heart - and a dab hand at guiding even the dullest of pupils.",
    "wikiUrl": "https://wiki.hoyolab.com/pc/genshin/entry/2265",
    "cdata": [
      "Dendro",
      "Bow",
      "Sumeru",
      "Dendro DMG Bonus",
      "5-Star"
    ],
    "rarity": 5,
    "weapon": "Bow",
    "region": "Sumeru"
  }
]
