[
  {
    "name": "Prototype Archaic",
    "desc": "An ancient greatsword discovered in the Blackcliff Forge. It swings with such an immense force that one feels it could cut straight through reality itself.",
    "rarity": 4,
    "source": "Forged",
    "passive": "On hit, Normal or Charged Attacks have a 50% chance to deal an additional 240% ATK DMG to opponents within a small AoE. Can only occur once every 15s.",
    "versionRelease": "1.0",
    "region": "Liyue",
    "family": "Weapon",
    "wikiUrl": "https://genshin.honeyhunterworld.com/i_n12406/?lang=EN",
    "affix": "Crush",
    "baseAtk": 43.73,
    "baseSubStat": 6,
    "subStatType": "Attack %",
    "images": {
      "icon": "http://res.cloudinary.com/dusbvc8ox/image/upload/v1703956863/FlameForge/weapons/weapon1703956874220.webp",
      "original": "http://res.cloudinary.com/dusbvc8ox/image/upload/v1703956873/FlameForge/weapons/weapon1703956883406.png",
      "awakened": "http://res.cloudinary.com/dusbvc8ox/image/upload/v1703956882/FlameForge/weapons/weapon1703956892661.png",
      "gacha": "http://res.cloudinary.com/dusbvc8ox/image/upload/v1703956890/FlameForge/weapons/weapon1703956900691.webp"
    }
  }
]
